setup.py
SmallSettings.egg-info/PKG-INFO
SmallSettings.egg-info/SOURCES.txt
SmallSettings.egg-info/dependency_links.txt
SmallSettings.egg-info/top_level.txt
smallsettings/README.md
smallsettings/__init__.py
smallsettings/factory.py
smallsettings/settings.py
smallsettings/tests/__init__.py
smallsettings/tests/base.py
smallsettings/tests/factory.py
smallsettings/tests/settings.py