Metadata-Version: 1.0
Name: SmallSettings
Version: 0.2.2
Summary: Simple settings functions for projects.
Home-page: UNKNOWN
Author: Dominik "Socek" Długajczy
Author-email: msocek@gmail.com
License: UNKNOWN
Platform: UNKNOWN
